cupyint/__init__.py
cupyint/integrate.py
cupyint-0.1.9.dist-info/LICENSE
cupyint-0.1.9.dist-info/METADATA
cupyint-0.1.9.dist-info/WHEEL
cupyint-0.1.9.dist-info/top_level.txt
cupyint-0.1.9.dist-info/RECORD
