Metadata-Version: 2.1
Name: cupyint
Version: 0.1.9
Summary: A CuPy-based numerical integration library
Home-page: https://github.com/ze-ouyang/cupyint
Author: Ze Ouyang
Author-email: ze_ouyang@utexas.edu
Classifier: Programming Language :: Python :: 3
Classifier: License :: OSI Approved :: MIT License
Classifier: Operating System :: OS Independent
Requires-Python: >=3.6
License-File: LICENSE
